Workbook

Sheet Portada
B2: PAPELES DE TRABAJO — ESTRUCTURACIÓN DE COSTOS DE UN PRODUCTO
B3: Análisis de Costos y Presupuestos — Marketing — 2026-II
B5: Empresa (caso) | C5: Dulce Misti E.I.R.L.
B6: Giro | C6: Elaboración y venta de tortas y postres (empresa de producción)
B7: Régimen tributario | C7: Régimen MYPE Tributario — afecto al IGV (18%)
B8: Ubicación | C8: Arequipa, Perú
B9: Producto principal | C9: Torta de Chocolate (molde 24 cm — 12 porciones)
B10: Producto secundario | C10: Cheesecake de Fresa (molde 22 cm — 10 porciones)
B11: Moneda | C11: Soles (S/)
B12: Docente | C12: Eduardo Luis Mamani Roque
B14: CONTENIDO DE LAS HOJAS DE TRABAJO
B15: 1. Parámetros | C15: Supuestos generales y factor de sobrecosto laboral (régimen general).
B16: 2. Compra de Insumos | C16: Cómo se compra cada insumo: proveedor, presentación, IGV como crédito fiscal, conversión de unidades, merma y costo unitario de uso.
B17: 3. Receta Torta | C17: Formulación detallada de la Torta de Chocolate y costo de materiales directos.
B18: 4. Receta Cheesecake | C18: Formulación del Cheesecake de Fresa.
B19: 5. Mano de Obra | C19: Costo empleador por hora del personal de producción.
B20: 6. CIF | C20: Costos indirectos de fabricación y tasa de aplicación.
B21: 7. Hoja de Costos | C21: Costo de producción unitario y fijación de precio (cost-plus).
B22: 8. Resumen | C22: Estructura del costo, comparación y margen de contribución.
B24: CÓDIGO DE COLORES (trazabilidad del modelo)
B25: Ejemplo | C25: Dato de entrada (azul, fondo amarillo): valor que se digita — precios, cantidades, sueldos. Al cambiarlo, todo el modelo se recalcula.
B26: Ejemplo | C26: Texto verde: valor traído automáticamente desde otra hoja (fórmula de enlace).
B27: Ejemplo | C27: Texto negro: resultado calculado con fórmula dentro de la misma hoja.
B29: Nota didáctica: el tratamiento del IGV y de las cargas laborales se presenta simplificado con fines de enseñanza. Los precios son referenciales del mercado de Arequipa. Todas las celdas de resultado son fórmulas: el archivo es un modelo vivo, no una tabla de números fijos.

Sheet Parámetros
B2: PARÁMETROS Y SUPUESTOS DEL MODELO
B4: Generales
B5: IGV | C5: 0.18
B6: Margen objetivo sobre el precio de venta | C6: 0.35
B7: Días productivos por mes | C7: 26
B8: Horas por día | C8: 8
B9: Meses productivos por año (descontando vacaciones) | C9: 11
B10: Factor de horas efectivamente productivas | C10: 0.85
B11: Producción mensual — Torta de Chocolate (und) | C11: 180
B12: Producción mensual — Cheesecake de Fresa (und) | C12: 120
B14: Cargas laborales — régimen laboral general (sobre el sueldo base)
B15: EsSalud | C15: =0.09 -> 0.09
B16: Gratificaciones (2 sueldos al año) | C16: =2/12 -> 0.16666667
B17: Bonificación extraordinaria s/ gratificación (Ley 30334) | C17: =C16*0.09 -> 0.015
B18: CTS (provisión anual / 12) | C18: =(1+1/6)/12 -> 0.097222222
B19: Factor de sobrecosto laboral (sueldo + cargas) | C19: =1+C15+C16+C17+C18 -> 1.3688889

Sheet Compra de Insumos
A1: HOJA 2 — COMPRA DE INSUMOS: DEL PROVEEDOR AL COSTO UNITARIO DE USO
A2: Regla del IGV: solo la compra con FACTURA de un bien GRAVADO genera crédito fiscal (el IGV se recupera y no es costo). Con boleta, sin comprobante o bien no gravado, el IGV forma parte del costo.
A3: Código | B3: Insumo | C3: Proveedor | D3: Presentación de compra | E3: Cant. de compra | F3: Unidad de compra | G3: ¿Gravado con IGV? | H3: Comprobante | I3: Precio de compra (con IGV) | J3: Crédito fiscal IGV | K3: Costo de adquisición | L3: Unidad de uso | M3: Factor de conversión | N3: Contenido total (unid. de uso) | O3: Costo unitario de uso | P3: Merma % | Q3: Costo unitario neto
A4: MP-001 | B4: Harina sin preparar | C4: Distribuidora Molitalia | D4: Saco 50 kg | E4: 50 | F4: kg | G4: Sí | H4: Factura | I4: 165 | J4: =IF(AND(G4="Sí",H4="Factura"),I4-I4/(1+Parámetros!C5),0) -> 25.169492 | K4: =I4-J4 -> 139.83051 | L4: g | M4: 1000 | N4: =E4*M4 -> 50000 | O4: =K4/N4 -> 0.0027966102 | P4: 0.02 | Q4: =O4/(1-P4) -> 0.0028536838
A5: MP-002 | B5: Azúcar blanca | C5: Makro | D5: Bolsa 5 kg | E5: 5 | F5: kg | G5: Sí | H5: Factura | I5: 22.5 | J5: =IF(AND(G5="Sí",H5="Factura"),I5-I5/(1+Parámetros!C5),0) -> 3.4322034 | K5: =I5-J5 -> 19.067797 | L5: g | M5: 1000 | N5: =E5*M5 -> 5000 | O5: =K5/N5 -> 0.0038135593 | P5: 0.01 | Q5: =O5/(1-P5) -> 0.0038520801
A6: MP-003 | B6: Huevos de gallina | C6: Mercado mayorista | D6: Jaba 30 unid | E6: 30 | F6: unid | G6: No | H6: Boleta | I6: 15 | J6: =IF(AND(G6="Sí",H6="Factura"),I6-I6/(1+Parámetros!C5),0) -> 0 | K6: =I6-J6 -> 15 | L6: unid | M6: 1 | N6: =E6*M6 -> 30 | O6: =K6/N6 -> 0.5 | P6: 0.03 | Q6: =O6/(1-P6) -> 0.51546392
A7: MP-004 | B7: Mantequilla sin sal | C7: Makro | D7: Pote 1 kg | E7: 1 | F7: kg | G7: Sí | H7: Factura | I7: 34 | J7: =IF(AND(G7="Sí",H7="Factura"),I7-I7/(1+Parámetros!C5),0) -> 5.1864407 | K7: =I7-J7 -> 28.813559 | L7: g | M7: 1000 | N7: =E7*M7 -> 1000 | O7: =K7/N7 -> 0.028813559 | P7: 0 | Q7: =O7/(1-P7) -> 0.028813559
A8: MP-005 | B8: Cacao en polvo | C8: Distribuidora repostería | D8: Bolsa 1 kg | E8: 1 | F8: kg | G8: Sí | H8: Factura | I8: 38 | J8: =IF(AND(G8="Sí",H8="Factura"),I8-I8/(1+Parámetros!C5),0) -> 5.7966102 | K8: =I8-J8 -> 32.20339 | L8: g | M8: 1000 | N8: =E8*M8 -> 1000 | O8: =K8/N8 -> 0.03220339 | P8: 0.01 | Q8: =O8/(1-P8) -> 0.032528677
A9: MP-006 | B9: Leche entera UHT | C9: Makro | D9: Caja 1 L | E9: 1 | F9: L | G9: Sí | H9: Factura | I9: 5.2 | J9: =IF(AND(G9="Sí",H9="Factura"),I9-I9/(1+Parámetros!C5),0) -> 0.79322034 | K9: =I9-J9 -> 4.4067797 | L9: ml | M9: 1000 | N9: =E9*M9 -> 1000 | O9: =K9/N9 -> 0.0044067797 | P9: 0 | Q9: =O9/(1-P9) -> 0.0044067797
A10: MP-007 | B10: Aceite vegetal | C10: Makro | D10: Botella 1 L | E10: 1 | F10: L | G10: Sí | H10: Factura | I10: 9.5 | J10: =IF(AND(G10="Sí",H10="Factura"),I10-I10/(1+Parámetros!C5),0) -> 1.4491525 | K10: =I10-J10 -> 8.0508475 | L10: ml | M10: 1000 | N10: =E10*M10 -> 1000 | O10: =K10/N10 -> 0.0080508475 | P10: 0 | Q10: =O10/(1-P10) -> 0.0080508475
A11: MP-008 | B11: Polvo de hornear | C11: Distribuidora repostería | D11: Pote 250 g | E11: 250 | F11: g | G11: Sí | H11: Factura | I11: 8 | J11: =IF(AND(G11="Sí",H11="Factura"),I11-I11/(1+Parámetros!C5),0) -> 1.220339 | K11: =I11-J11 -> 6.779661 | L11: g | M11: 1 | N11: =E11*M11 -> 250 | O11: =K11/N11 -> 0.027118644 | P11: 0 | Q11: =O11/(1-P11) -> 0.027118644
A12: MP-009 | B12: Esencia de vainilla | C12: Distribuidora repostería | D12: Frasco 120 ml | E12: 120 | F12: ml | G12: Sí | H12: Factura | I12: 7.5 | J12: =IF(AND(G12="Sí",H12="Factura"),I12-I12/(1+Parámetros!C5),0) -> 1.1440678 | K12: =I12-J12 -> 6.3559322 | L12: ml | M12: 1 | N12: =E12*M12 -> 120 | O12: =K12/N12 -> 0.052966102 | P12: 0 | Q12: =O12/(1-P12) -> 0.052966102
A13: MP-010 | B13: Sal | C13: Mercado mayorista | D13: Bolsa 1 kg | E13: 1 | F13: kg | G13: Sí | H13: Boleta | I13: 2.5 | J13: =IF(AND(G13="Sí",H13="Factura"),I13-I13/(1+Parámetros!C5),0) -> 0 | K13: =I13-J13 -> 2.5 | L13: g | M13: 1000 | N13: =E13*M13 -> 1000 | O13: =K13/N13 -> 0.0025 | P13: 0 | Q13: =O13/(1-P13) -> 0.0025
A14: MP-011 | B14: Chocolate cobertura bitter | C14: Distribuidora repostería | D14: Barra 1 kg | E14: 1 | F14: kg | G14: Sí | H14: Factura | I14: 42 | J14: =IF(AND(G14="Sí",H14="Factura"),I14-I14/(1+Parámetros!C5),0) -> 6.4067797 | K14: =I14-J14 -> 35.59322 | L14: g | M14: 1000 | N14: =E14*M14 -> 1000 | O14: =K14/N14 -> 0.03559322 | P14: 0.01 | Q14: =O14/(1-P14) -> 0.035952748
A15: MP-012 | B15: Crema de leche | C15: Makro | D15: Caja 1 L | E15: 1 | F15: L | G15: Sí | H15: Factura | I15: 18 | J15: =IF(AND(G15="Sí",H15="Factura"),I15-I15/(1+Parámetros!C5),0) -> 2.7457627 | K15: =I15-J15 -> 15.254237 | L15: ml | M15: 1000 | N15: =E15*M15 -> 1000 | O15: =K15/N15 -> 0.015254237 | P15: 0.02 | Q15: =O15/(1-P15) -> 0.015565548
A16: MP-013 | B16: Queso crema | C16: Makro | D16: Pote 1.8 kg | E16: 1.8 | F16: kg | G16: Sí | H16: Factura | I16: 46 | J16: =IF(AND(G16="Sí",H16="Factura"),I16-I16/(1+Parámetros!C5),0) -> 7.0169492 | K16: =I16-J16 -> 38.983051 | L16: g | M16: 1000 | N16: =E16*M16 -> 1800 | O16: =K16/N16 -> 0.02165725 | P16: 0 | Q16: =O16/(1-P16) -> 0.02165725
A17: MP-014 | B17: Galleta de vainilla | C17: Makro | D17: Paquete 400 g | E17: 400 | F17: g | G17: Sí | H17: Boleta | I17: 6.5 | J17: =IF(AND(G17="Sí",H17="Factura"),I17-I17/(1+Parámetros!C5),0) -> 0 | K17: =I17-J17 -> 6.5 | L17: g | M17: 1 | N17: =E17*M17 -> 400 | O17: =K17/N17 -> 0.01625 | P17: 0.03 | Q17: =O17/(1-P17) -> 0.016752577
A18: MP-015 | B18: Fresas frescas | C18: Mercado mayorista | D18: Kilogramo | E18: 1 | F18: kg | G18: No | H18: Boleta | I18: 9 | J18: =IF(AND(G18="Sí",H18="Factura"),I18-I18/(1+Parámetros!C5),0) -> 0 | K18: =I18-J18 -> 9 | L18: g | M18: 1000 | N18: =E18*M18 -> 1000 | O18: =K18/N18 -> 0.009 | P18: 0.12 | Q18: =O18/(1-P18) -> 0.010227273
A19: MP-016 | B19: Gelatina sin sabor | C19: Distribuidora repostería | D19: Caja 250 g | E19: 250 | F19: g | G19: Sí | H19: Factura | I19: 12 | J19: =IF(AND(G19="Sí",H19="Factura"),I19-I19/(1+Parámetros!C5),0) -> 1.8305085 | K19: =I19-J19 -> 10.169492 | L19: g | M19: 1 | N19: =E19*M19 -> 250 | O19: =K19/N19 -> 0.040677966 | P19: 0 | Q19: =O19/(1-P19) -> 0.040677966
A20: MP-017 | B20: Azúcar impalpable | C20: Distribuidora repostería | D20: Bolsa 1 kg | E20: 1 | F20: kg | G20: Sí | H20: Factura | I20: 7.5 | J20: =IF(AND(G20="Sí",H20="Factura"),I20-I20/(1+Parámetros!C5),0) -> 1.1440678 | K20: =I20-J20 -> 6.3559322 | L20: g | M20: 1000 | N20: =E20*M20 -> 1000 | O20: =K20/N20 -> 0.0063559322 | P20: 0.01 | Q20: =O20/(1-P20) -> 0.0064201335
A21: EM-001 | B21: Base de cartón torta 24 cm | C21: Envases del Sur | D21: Paquete 25 unid | E21: 25 | F21: unid | G21: Sí | H21: Factura | I21: 20 | J21: =IF(AND(G21="Sí",H21="Factura"),I21-I21/(1+Parámetros!C5),0) -> 3.0508475 | K21: =I21-J21 -> 16.949153 | L21: unid | M21: 1 | N21: =E21*M21 -> 25 | O21: =K21/N21 -> 0.6779661 | P21: 0 | Q21: =O21/(1-P21) -> 0.6779661
A22: EM-002 | B22: Caja para torta 24 cm | C22: Envases del Sur | D22: Paquete 25 unid | E22: 25 | F22: unid | G22: Sí | H22: Factura | I22: 62.5 | J22: =IF(AND(G22="Sí",H22="Factura"),I22-I22/(1+Parámetros!C5),0) -> 9.5338983 | K22: =I22-J22 -> 52.966102 | L22: unid | M22: 1 | N22: =E22*M22 -> 25 | O22: =K22/N22 -> 2.1186441 | P22: 0 | Q22: =O22/(1-P22) -> 2.1186441
A23: EM-003 | B23: Etiqueta / sticker | C23: Imprenta local | D23: Rollo 500 unid | E23: 500 | F23: unid | G23: Sí | H23: Factura | I23: 45 | J23: =IF(AND(G23="Sí",H23="Factura"),I23-I23/(1+Parámetros!C5),0) -> 6.8644068 | K23: =I23-J23 -> 38.135593 | L23: unid | M23: 1 | N23: =E23*M23 -> 500 | O23: =K23/N23 -> 0.076271186 | P23: 0.02 | Q23: =O23/(1-P23) -> 0.077827741
A24: EM-004 | B24: Base y caja cheesecake | C24: Envases del Sur | D24: Paquete 50 unid | E24: 50 | F24: unid | G24: Sí | H24: Factura | I24: 90 | J24: =IF(AND(G24="Sí",H24="Factura"),I24-I24/(1+Parámetros!C5),0) -> 13.728814 | K24: =I24-J24 -> 76.271186 | L24: unid | M24: 1 | N24: =E24*M24 -> 50 | O24: =K24/N24 -> 1.5254237 | P24: 0 | Q24: =O24/(1-P24) -> 1.5254237

Sheet Receta Torta
A1: HOJA 3 — RECETA Y COSTO DE MATERIALES: TORTA DE CHOCOLATE
A3: Producto | B3: Torta de Chocolate
A4: Molde | B4: 24 cm de diámetro
A5: Unidad de costeo | B5: 1 torta entera
A6: Elaboración | B6: Bizcocho de chocolate + cobertura de ganache
A8: Código | B8: Insumo | C8: Cantidad | D8: Unidad | E8: Costo unitario neto | F8: Costo total | G8: % del costo
A9: Materia prima directa
A10: MP-001 | B10: =INDEX('Compra de Insumos'!$B$4:$B$24,MATCH(A10,'Compra de Insumos'!$A$4:$A$24,0)) -> Harina sin preparar | C10: 500 | D10: =INDEX('Compra de Insumos'!$L$4:$L$24,MATCH(A10,'Compra de Insumos'!$A$4:$A$24,0)) -> g | E10: =INDEX('Compra de Insumos'!$Q$4:$Q$24,MATCH(A10,'Compra de Insumos'!$A$4:$A$24,0)) -> 0.0028536838 | F10: =C10*E10 -> 1.4268419 | G10: =F10/F28 -> 0.049848895
A11: MP-002 | B11: =INDEX('Compra de Insumos'!$B$4:$B$24,MATCH(A11,'Compra de Insumos'!$A$4:$A$24,0)) -> Azúcar blanca | C11: 400 | D11: =INDEX('Compra de Insumos'!$L$4:$L$24,MATCH(A11,'Compra de Insumos'!$A$4:$A$24,0)) -> g | E11: =INDEX('Compra de Insumos'!$Q$4:$Q$24,MATCH(A11,'Compra de Insumos'!$A$4:$A$24,0)) -> 0.0038520801 | F11: =C11*E11 -> 1.540832 | G11: =F11/F28 -> 0.053831314
A12: MP-005 | B12: =INDEX('Compra de Insumos'!$B$4:$B$24,MATCH(A12,'Compra de Insumos'!$A$4:$A$24,0)) -> Cacao en polvo | C12: 90 | D12: =INDEX('Compra de Insumos'!$L$4:$L$24,MATCH(A12,'Compra de Insumos'!$A$4:$A$24,0)) -> g | E12: =INDEX('Compra de Insumos'!$Q$4:$Q$24,MATCH(A12,'Compra de Insumos'!$A$4:$A$24,0)) -> 0.032528677 | F12: =C12*E12 -> 2.9275809 | G12: =F12/F28 -> 0.1022795
A13: MP-003 | B13: =INDEX('Compra de Insumos'!$B$4:$B$24,MATCH(A13,'Compra de Insumos'!$A$4:$A$24,0)) -> Huevos de gallina | C13: 5 | D13: =INDEX('Compra de Insumos'!$L$4:$L$24,MATCH(A13,'Compra de Insumos'!$A$4:$A$24,0)) -> unid | E13: =INDEX('Compra de Insumos'!$Q$4:$Q$24,MATCH(A13,'Compra de Insumos'!$A$4:$A$24,0)) -> 0.51546392 | F13: =C13*E13 -> 2.5773196 | G13: =F13/F28 -> 0.090042584
A14: MP-004 | B14: =INDEX('Compra de Insumos'!$B$4:$B$24,MATCH(A14,'Compra de Insumos'!$A$4:$A$24,0)) -> Mantequilla sin sal | C14: 150 | D14: =INDEX('Compra de Insumos'!$L$4:$L$24,MATCH(A14,'Compra de Insumos'!$A$4:$A$24,0)) -> g | E14: =INDEX('Compra de Insumos'!$Q$4:$Q$24,MATCH(A14,'Compra de Insumos'!$A$4:$A$24,0)) -> 0.028813559 | F14: =C14*E14 -> 4.3220339 | G14: =F14/F28 -> 0.15099683
A15: MP-007 | B15: =INDEX('Compra de Insumos'!$B$4:$B$24,MATCH(A15,'Compra de Insumos'!$A$4:$A$24,0)) -> Aceite vegetal | C15: 80 | D15: =INDEX('Compra de Insumos'!$L$4:$L$24,MATCH(A15,'Compra de Insumos'!$A$4:$A$24,0)) -> ml | E15: =INDEX('Compra de Insumos'!$Q$4:$Q$24,MATCH(A15,'Compra de Insumos'!$A$4:$A$24,0)) -> 0.0080508475 | F15: =C15*E15 -> 0.6440678 | G15: =F15/F28 -> 0.022501489
A16: MP-006 | B16: =INDEX('Compra de Insumos'!$B$4:$B$24,MATCH(A16,'Compra de Insumos'!$A$4:$A$24,0)) -> Leche entera UHT | C16: 240 | D16: =INDEX('Compra de Insumos'!$L$4:$L$24,MATCH(A16,'Compra de Insumos'!$A$4:$A$24,0)) -> ml | E16: =INDEX('Compra de Insumos'!$Q$4:$Q$24,MATCH(A16,'Compra de Insumos'!$A$4:$A$24,0)) -> 0.0044067797 | F16: =C16*E16 -> 1.0576271 | G16: =F16/F28 -> 0.036949814
A17: MP-008 | B17: =INDEX('Compra de Insumos'!$B$4:$B$24,MATCH(A17,'Compra de Insumos'!$A$4:$A$24,0)) -> Polvo de hornear | C17: 15 | D17: =INDEX('Compra de Insumos'!$L$4:$L$24,MATCH(A17,'Compra de Insumos'!$A$4:$A$24,0)) -> g | E17: =INDEX('Compra de Insumos'!$Q$4:$Q$24,MATCH(A17,'Compra de Insumos'!$A$4:$A$24,0)) -> 0.027118644 | F17: =C17*E17 -> 0.40677966 | G17: =F17/F28 -> 0.014211467
A18: MP-009 | B18: =INDEX('Compra de Insumos'!$B$4:$B$24,MATCH(A18,'Compra de Insumos'!$A$4:$A$24,0)) -> Esencia de vainilla | C18: 10 | D18: =INDEX('Compra de Insumos'!$L$4:$L$24,MATCH(A18,'Compra de Insumos'!$A$4:$A$24,0)) -> ml | E18: =INDEX('Compra de Insumos'!$Q$4:$Q$24,MATCH(A18,'Compra de Insumos'!$A$4:$A$24,0)) -> 0.052966102 | F18: =C18*E18 -> 0.52966102 | G18: =F18/F28 -> 0.018504514
A19: MP-010 | B19: =INDEX('Compra de Insumos'!$B$4:$B$24,MATCH(A19,'Compra de Insumos'!$A$4:$A$24,0)) -> Sal | C19: 5 | D19: =INDEX('Compra de Insumos'!$L$4:$L$24,MATCH(A19,'Compra de Insumos'!$A$4:$A$24,0)) -> g | E19: =INDEX('Compra de Insumos'!$Q$4:$Q$24,MATCH(A19,'Compra de Insumos'!$A$4:$A$24,0)) -> 0.0025 | F19: =C19*E19 -> 0.0125 | G19: =F19/F28 -> 0.00043670653
A20: MP-011 | B20: =INDEX('Compra de Insumos'!$B$4:$B$24,MATCH(A20,'Compra de Insumos'!$A$4:$A$24,0)) -> Chocolate cobertura bitter | C20: 200 | D20: =INDEX('Compra de Insumos'!$L$4:$L$24,MATCH(A20,'Compra de Insumos'!$A$4:$A$24,0)) -> g | E20: =INDEX('Compra de Insumos'!$Q$4:$Q$24,MATCH(A20,'Compra de Insumos'!$A$4:$A$24,0)) -> 0.035952748 | F20: =C20*E20 -> 7.1905496 | G20: =F20/F28 -> 0.2512128
A21: MP-012 | B21: =INDEX('Compra de Insumos'!$B$4:$B$24,MATCH(A21,'Compra de Insumos'!$A$4:$A$24,0)) -> Crema de leche | C21: 200 | D21: =INDEX('Compra de Insumos'!$L$4:$L$24,MATCH(A21,'Compra de Insumos'!$A$4:$A$24,0)) -> ml | E21: =INDEX('Compra de Insumos'!$Q$4:$Q$24,MATCH(A21,'Compra de Insumos'!$A$4:$A$24,0)) -> 0.015565548 | F21: =C21*E21 -> 3.1131097 | G21: =F21/F28 -> 0.10876123
E22: Subtotal materia prima directa | F22: =SUM(F10:F21) -> 25.748903
A23: Material de empaque directo
A24: EM-001 | B24: =INDEX('Compra de Insumos'!$B$4:$B$24,MATCH(A24,'Compra de Insumos'!$A$4:$A$24,0)) -> Base de cartón torta 24 cm | C24: 1 | D24: =INDEX('Compra de Insumos'!$L$4:$L$24,MATCH(A24,'Compra de Insumos'!$A$4:$A$24,0)) -> unid | E24: =INDEX('Compra de Insumos'!$Q$4:$Q$24,MATCH(A24,'Compra de Insumos'!$A$4:$A$24,0)) -> 0.6779661 | F24: =C24*E24 -> 0.6779661 | G24: =F24/F28 -> 0.023685778
A25: EM-002 | B25: =INDEX('Compra de Insumos'!$B$4:$B$24,MATCH(A25,'Compra de Insumos'!$A$4:$A$24,0)) -> Caja para torta 24 cm | C25: 1 | D25: =INDEX('Compra de Insumos'!$L$4:$L$24,MATCH(A25,'Compra de Insumos'!$A$4:$A$24,0)) -> unid | E25: =INDEX('Compra de Insumos'!$Q$4:$Q$24,MATCH(A25,'Compra de Insumos'!$A$4:$A$24,0)) -> 2.1186441 | F25: =C25*E25 -> 2.1186441 | G25: =F25/F28 -> 0.074018056
A26: EM-003 | B26: =INDEX('Compra de Insumos'!$B$4:$B$24,MATCH(A26,'Compra de Insumos'!$A$4:$A$24,0)) -> Etiqueta / sticker | C26: 1 | D26: =INDEX('Compra de Insumos'!$L$4:$L$24,MATCH(A26,'Compra de Insumos'!$A$4:$A$24,0)) -> unid | E26: =INDEX('Compra de Insumos'!$Q$4:$Q$24,MATCH(A26,'Compra de Insumos'!$A$4:$A$24,0)) -> 0.077827741 | F26: =C26*E26 -> 0.077827741 | G26: =F26/F28 -> 0.0027190306
E27: Subtotal empaque directo | F27: =SUM(F24:F26) -> 2.8744379
E28: COSTO DE MATERIALES DIRECTOS (por unidad) | F28: =F22+F27 -> 28.623341
A30: Rinde (porciones) | B30: 12 | D30: Costo de materiales por porción | E30: =F28/B30 -> 2.3852784

Sheet Receta Cheesecake
A1: HOJA 4 — RECETA Y COSTO DE MATERIALES: CHEESECAKE DE FRESA
A3: Producto | B3: Cheesecake de Fresa
A4: Molde | B4: 22 cm de diámetro
A5: Unidad de costeo | B5: 1 cheesecake entero
A6: Elaboración | B6: Base de galleta + relleno de queso + gelée de fresa
A8: Código | B8: Insumo | C8: Cantidad | D8: Unidad | E8: Costo unitario neto | F8: Costo total | G8: % del costo
A9: Materia prima directa
A10: MP-014 | B10: =INDEX('Compra de Insumos'!$B$4:$B$24,MATCH(A10,'Compra de Insumos'!$A$4:$A$24,0)) -> Galleta de vainilla | C10: 300 | D10: =INDEX('Compra de Insumos'!$L$4:$L$24,MATCH(A10,'Compra de Insumos'!$A$4:$A$24,0)) -> g | E10: =INDEX('Compra de Insumos'!$Q$4:$Q$24,MATCH(A10,'Compra de Insumos'!$A$4:$A$24,0)) -> 0.016752577 | F10: =C10*E10 -> 5.0257732 | G10: =F10/F24 -> 0.14993197
A11: MP-004 | B11: =INDEX('Compra de Insumos'!$B$4:$B$24,MATCH(A11,'Compra de Insumos'!$A$4:$A$24,0)) -> Mantequilla sin sal | C11: 120 | D11: =INDEX('Compra de Insumos'!$L$4:$L$24,MATCH(A11,'Compra de Insumos'!$A$4:$A$24,0)) -> g | E11: =INDEX('Compra de Insumos'!$Q$4:$Q$24,MATCH(A11,'Compra de Insumos'!$A$4:$A$24,0)) -> 0.028813559 | F11: =C11*E11 -> 3.4576271 | G11: =F11/F24 -> 0.10315007
A12: MP-013 | B12: =INDEX('Compra de Insumos'!$B$4:$B$24,MATCH(A12,'Compra de Insumos'!$A$4:$A$24,0)) -> Queso crema | C12: 600 | D12: =INDEX('Compra de Insumos'!$L$4:$L$24,MATCH(A12,'Compra de Insumos'!$A$4:$A$24,0)) -> g | E12: =INDEX('Compra de Insumos'!$Q$4:$Q$24,MATCH(A12,'Compra de Insumos'!$A$4:$A$24,0)) -> 0.02165725 | F12: =C12*E12 -> 12.99435 | G12: =F12/F24 -> 0.38765548
A13: MP-017 | B13: =INDEX('Compra de Insumos'!$B$4:$B$24,MATCH(A13,'Compra de Insumos'!$A$4:$A$24,0)) -> Azúcar impalpable | C13: 150 | D13: =INDEX('Compra de Insumos'!$L$4:$L$24,MATCH(A13,'Compra de Insumos'!$A$4:$A$24,0)) -> g | E13: =INDEX('Compra de Insumos'!$Q$4:$Q$24,MATCH(A13,'Compra de Insumos'!$A$4:$A$24,0)) -> 0.0064201335 | F13: =C13*E13 -> 0.96302003 | G13: =F13/F24 -> 0.028729408
A14: MP-003 | B14: =INDEX('Compra de Insumos'!$B$4:$B$24,MATCH(A14,'Compra de Insumos'!$A$4:$A$24,0)) -> Huevos de gallina | C14: 3 | D14: =INDEX('Compra de Insumos'!$L$4:$L$24,MATCH(A14,'Compra de Insumos'!$A$4:$A$24,0)) -> unid | E14: =INDEX('Compra de Insumos'!$Q$4:$Q$24,MATCH(A14,'Compra de Insumos'!$A$4:$A$24,0)) -> 0.51546392 | F14: =C14*E14 -> 1.5463918 | G14: =F14/F24 -> 0.046132914
A15: MP-012 | B15: =INDEX('Compra de Insumos'!$B$4:$B$24,MATCH(A15,'Compra de Insumos'!$A$4:$A$24,0)) -> Crema de leche | C15: 200 | D15: =INDEX('Compra de Insumos'!$L$4:$L$24,MATCH(A15,'Compra de Insumos'!$A$4:$A$24,0)) -> ml | E15: =INDEX('Compra de Insumos'!$Q$4:$Q$24,MATCH(A15,'Compra de Insumos'!$A$4:$A$24,0)) -> 0.015565548 | F15: =C15*E15 -> 3.1131097 | G15: =F15/F24 -> 0.09287221
A16: MP-016 | B16: =INDEX('Compra de Insumos'!$B$4:$B$24,MATCH(A16,'Compra de Insumos'!$A$4:$A$24,0)) -> Gelatina sin sabor | C16: 20 | D16: =INDEX('Compra de Insumos'!$L$4:$L$24,MATCH(A16,'Compra de Insumos'!$A$4:$A$24,0)) -> g | E16: =INDEX('Compra de Insumos'!$Q$4:$Q$24,MATCH(A16,'Compra de Insumos'!$A$4:$A$24,0)) -> 0.040677966 | F16: =C16*E16 -> 0.81355932 | G16: =F16/F24 -> 0.024270604
A17: MP-015 | B17: =INDEX('Compra de Insumos'!$B$4:$B$24,MATCH(A17,'Compra de Insumos'!$A$4:$A$24,0)) -> Fresas frescas | C17: 350 | D17: =INDEX('Compra de Insumos'!$L$4:$L$24,MATCH(A17,'Compra de Insumos'!$A$4:$A$24,0)) -> g | E17: =INDEX('Compra de Insumos'!$Q$4:$Q$24,MATCH(A17,'Compra de Insumos'!$A$4:$A$24,0)) -> 0.010227273 | F17: =C17*E17 -> 3.5795455 | G17: =F17/F24 -> 0.10678721
A18: MP-009 | B18: =INDEX('Compra de Insumos'!$B$4:$B$24,MATCH(A18,'Compra de Insumos'!$A$4:$A$24,0)) -> Esencia de vainilla | C18: 8 | D18: =INDEX('Compra de Insumos'!$L$4:$L$24,MATCH(A18,'Compra de Insumos'!$A$4:$A$24,0)) -> ml | E18: =INDEX('Compra de Insumos'!$Q$4:$Q$24,MATCH(A18,'Compra de Insumos'!$A$4:$A$24,0)) -> 0.052966102 | F18: =C18*E18 -> 0.42372881 | G18: =F18/F24 -> 0.01264094
E19: Subtotal materia prima directa | F19: =SUM(F10:F18) -> 31.917106
A20: Material de empaque directo
A21: EM-004 | B21: =INDEX('Compra de Insumos'!$B$4:$B$24,MATCH(A21,'Compra de Insumos'!$A$4:$A$24,0)) -> Base y caja cheesecake | C21: 1 | D21: =INDEX('Compra de Insumos'!$L$4:$L$24,MATCH(A21,'Compra de Insumos'!$A$4:$A$24,0)) -> unid | E21: =INDEX('Compra de Insumos'!$Q$4:$Q$24,MATCH(A21,'Compra de Insumos'!$A$4:$A$24,0)) -> 1.5254237 | F21: =C21*E21 -> 1.5254237 | G21: =F21/F24 -> 0.045507383
A22: EM-003 | B22: =INDEX('Compra de Insumos'!$B$4:$B$24,MATCH(A22,'Compra de Insumos'!$A$4:$A$24,0)) -> Etiqueta / sticker | C22: 1 | D22: =INDEX('Compra de Insumos'!$L$4:$L$24,MATCH(A22,'Compra de Insumos'!$A$4:$A$24,0)) -> unid | E22: =INDEX('Compra de Insumos'!$Q$4:$Q$24,MATCH(A22,'Compra de Insumos'!$A$4:$A$24,0)) -> 0.077827741 | F22: =C22*E22 -> 0.077827741 | G22: =F22/F24 -> 0.0023218053
E23: Subtotal empaque directo | F23: =SUM(F21:F22) -> 1.6032515
E24: COSTO DE MATERIALES DIRECTOS (por unidad) | F24: =F19+F23 -> 33.520357
A26: Rinde (porciones) | B26: 10 | D26: Costo de materiales por porción | E26: =F24/B26 -> 3.3520357

Sheet Mano de Obra
B1: HOJA 5 — COSTO DE LA MANO DE OBRA DIRECTA (COSTO EMPLEADOR)
B3: Concepto | C3: Maestro pastelero | D3: Ayudante de pastelería | E3: Nota
B4: Sueldo básico mensual | C4: 1600 | D4: 1300 | E4: Dato de la planilla.
B5: (x) Factor de sobrecosto laboral | C5: =Parámetros!C19 -> 1.3688889 | D5: =Parámetros!C19 -> 1.3688889 | E5: EsSalud + gratificaciones + bonif. + CTS (ver Parámetros).
B6: (=) Costo empleador mensual | C6: =C4*C5 -> 2190.2222 | D6: =D4*D5 -> 1779.5556 | E6: Lo que realmente cuesta el trabajador al mes.
B7: (x) 12 meses | C7: 12 | D7: 12
B8: (=) Costo empleador anual | C8: =C6*C7 -> 26282.667 | D8: =D6*D7 -> 21354.667
B9: Horas productivas al año | C9: =Parámetros!C7*Parámetros!C8*Parámetros!C9*Parámetros!C10 -> 1944.8 | D9: =Parámetros!C7*Parámetros!C8*Parámetros!C9*Parámetros!C10 -> 1944.8 | E9: Días x horas x meses productivos x factor de eficiencia.
B10: (=) Costo por hora productiva | C10: =C8/C9 -> 13.514329 | D10: =D8/D9 -> 10.980392 | E10: Base para costear el tiempo de cada producto.
B12: Tiempo de mano de obra por producto
B13: Producto | C13: Minutos maestro | D13: Minutos ayudante | E13: Costo MOD por unidad
B14: Torta de Chocolate | C14: 30 | D14: 25 | E14: =C14/60*C10+D14/60*D10 -> 11.332328
B15: Cheesecake de Fresa | C15: 25 | D15: 20 | E15: =C15/60*C10+D15/60*D10 -> 9.2911011

Sheet CIF
B1: HOJA 6 — COSTOS INDIRECTOS DE FABRICACIÓN (CIF) Y TASA DE APLICACIÓN
B3: Concepto (mensual) | C3: Importe | D3: Nota
B4: Alquiler del área de producción | C4: 1200 | D4: Parte del local dedicada a producción.
B5: Energía eléctrica | C5: 650 | D5: Horno, batidora industrial, refrigeración.
B6: Gas (GLP) | C6: 380
B7: Agua | C7: 120
B8: Depreciación de equipos | C8: 250 | D8: Horno, batidora, refrigeradora (mensual).
B9: Mano de obra indirecta | C9: 500 | D9: Limpieza y supervisión parcial.
B10: Insumos indirectos | C10: 180 | D10: Film, guantes, papel manteca, detergente.
B11: Mantenimiento de equipos | C11: 150
B12: TOTAL CIF MENSUAL | C12: =SUM(C4:C11) -> 3430
B14: Base de asignación: horas de mano de obra directa
B15: Concepto | C15: Valor | D15: Fórmula / nota
B16: Horas MOD/mes — Torta | C16: =('Mano de Obra'!C14+'Mano de Obra'!D14)/60*Parámetros!C11 -> 165 | D16: (min maestro + min ayudante)/60 x producción mensual
B17: Horas MOD/mes — Cheesecake | C17: =('Mano de Obra'!C15+'Mano de Obra'!D15)/60*Parámetros!C12 -> 90
B18: Total horas MOD/mes | C18: =C16+C17 -> 255
B19: Tasa de aplicación CIF (S/ por hora MOD) | C19: =C12/C18 -> 13.45098 | D19: Total CIF mensual ÷ total horas MOD mensuales.
B20: CIF por unidad — Torta | C20: =('Mano de Obra'!C14+'Mano de Obra'!D14)/60*C19 -> 12.330065 | D20: Horas MOD por torta x tasa CIF.
B21: CIF por unidad — Cheesecake | C21: =('Mano de Obra'!C15+'Mano de Obra'!D15)/60*C19 -> 10.088235

Sheet Hoja de Costos
B1: HOJA 7 — HOJA DE COSTO UNITARIO Y FIJACIÓN DE PRECIO
B3: Componente | C3: Torta de Chocolate | D3: Cheesecake de Fresa | E3: Nota
B4: Materiales directos (MP + empaque) | C4: ='Receta Torta'!F28 -> 28.623341 | D4: ='Receta Cheesecake'!F24 -> 33.520357 | E4: Desde las hojas de receta.
B5: Mano de obra directa | C5: ='Mano de Obra'!E14 -> 11.332328 | D5: ='Mano de Obra'!E15 -> 9.2911011 | E5: Desde la hoja de mano de obra.
B6: Costos indirectos de fabricación | C6: =CIF!C20 -> 12.330065 | D6: =CIF!C21 -> 10.088235 | E6: CIF aplicado por horas MOD.
B7: (=) COSTO DE PRODUCCIÓN UNITARIO | C7: =SUM(C4:C6) -> 52.285734 | D7: =SUM(D4:D6) -> 52.899693
B8: Rinde (porciones) | C8: 12 | D8: 10 | E8: Porciones por unidad.
B9: Costo de producción por porción | C9: =C7/C8 -> 4.3571445 | D9: =D7/D8 -> 5.2899693
B11: Fijación de precio — método cost-plus (margen sobre el precio de venta)
B12: Margen objetivo sobre precio de venta | C12: =Parámetros!C6 -> 0.35 | D12: =Parámetros!C6 -> 0.35
B13: Precio de venta sin IGV | C13: =C7/(1-C12) -> 80.439591 | D13: =D7/(1-D12) -> 81.384144 | E13: Costo ÷ (1 − margen).
B14: IGV (18%) | C14: =C13*Parámetros!C5 -> 14.479126 | D14: =D13*Parámetros!C5 -> 14.649146
B15: (=) PRECIO DE VENTA AL PÚBLICO (con IGV) | C15: =C13+C14 -> 94.918718 | D15: =D13+D14 -> 96.03329
B16: Utilidad por unidad (sin IGV) | C16: =C13-C7 -> 28.153857 | D16: =D13-D7 -> 28.48445
B17: Margen sobre el costo (referencial) | C17: =C16/C7 -> 0.53846154 | D17: =D16/D7 -> 0.53846154 | E17: Utilidad ÷ costo: distinto del margen sobre venta.

Sheet Resumen
B1: HOJA 8 — RESUMEN: ESTRUCTURA DEL COSTO Y MARGEN DE CONTRIBUCIÓN
B3: Indicador | C3: Torta de Chocolate | D3: Cheesecake de Fresa
B4: Materiales directos | C4: ='Hoja de Costos'!C4 -> 28.623341 | D4: ='Hoja de Costos'!D4 -> 33.520357
B5: Mano de obra directa | C5: ='Hoja de Costos'!C5 -> 11.332328 | D5: ='Hoja de Costos'!D5 -> 9.2911011
B6: Costos indirectos de fabricación | C6: ='Hoja de Costos'!C6 -> 12.330065 | D6: ='Hoja de Costos'!D6 -> 10.088235
B7: (=) Costo de producción unitario | C7: ='Hoja de Costos'!C7 -> 52.285734 | D7: ='Hoja de Costos'!D7 -> 52.899693
B9: Estructura porcentual del costo
B10: % Materiales | C10: =C4/C7 -> 0.54744074 | D10: =D4/D7 -> 0.63365882
B11: % Mano de obra | C11: =C5/C7 -> 0.21673843 | D11: =D5/D7 -> 0.1756362
B12: % CIF | C12: =C6/C7 -> 0.23582083 | D12: =D6/D7 -> 0.19070499
B14: Precio y rentabilidad por unidad
B15: Precio de venta sin IGV | C15: ='Hoja de Costos'!C13 -> 80.439591 | D15: ='Hoja de Costos'!D13 -> 81.384144
B16: Precio al público (con IGV) | C16: ='Hoja de Costos'!C15 -> 94.918718 | D16: ='Hoja de Costos'!D15 -> 96.03329
B17: Margen de contribución unitario | C17: =C15-C4 -> 51.81625 | D17: =D15-D4 -> 47.863787 | E17: Precio sin IGV − costo variable (materiales).
B18: Razón de contribución | C18: =C17/C15 -> 0.64416352 | D18: =D17/D15 -> 0.58812177
B20: Lectura: en repostería la mano de obra y los CIF pesan tanto como los insumos; costear solo la receta subestima el costo real. El margen de contribución (que aquí trata los materiales como costo variable) sirve para decisiones de volumen y punto de equilibrio.
