Workbook

Sheet Instrucciones
A1: GUÍA DE LABORATORIO - SESIÓN 4: ESTRATEGIAS DE PRECIOS E INGENIERÍA DEL MARGEN
A3: Curso: Análisis de Costos y Presupuestos. Caso: Dulce Sabor, panadería artesanal.
A5: Como usar este libro:
A6: 1. Las celdas con datos ya escritos son información del caso. No las modifique salvo que el docente lo indique.
A7: 2. Las celdas vacías dentro de las tablas se completan SIEMPRE con una fórmula, nunca con un resultado escrito a mano.
A8: 3. Ejemplo de lo que se espera: si el importe de un insumo es cantidad por precio unitario, escriba =B5*D5 y no 25.20
A9: 4. Los datos generales están en la hoja Datos. Refiérase a ellos con referencias absolutas, por ejemplo =Datos!$B$7
A10: 5. Cada hoja termina con una línea de conclusión. Escriba ahí una frase corta con la lectura del equipo.
A12: Hojas del libro:
A13: Datos Parámetros generales y costos fijos mensuales de la línea de torta.
A14: Caso 1 Costo unitario real de la torta de chocolate.
A15: Caso 2 Cost-Plus y la diferencia entre recargo y margen bruto.
... A23: Entrega: un archivo por equipo, por el canal digital del curso. No se imprime nada.

Sheet Datos
A1: DULCE SABOR - DATOS BASE
A2: Información del caso. Estas celdas no se modifican.
A4: Parámetros generales
A5: Concepto | B5: Valor
A6: Volumen mensual actual (tortas) | B6: 400
A7: Precio de venta actual (S/) | B7: 60
A8: Meta de margen bruto de la empresa | B8: 0.4
A10: Costos fijos mensuales asignados a la línea de torta (S/)
A11: Concepto | B11: Importe
A12: Alquiler del local (parte asignada) | B12: 1500
A13: Sueldo fijo del maestro pastelero | B13: 1500
A14: Depreciación de equipos | B14: 300
A15: Energía fija del horno | B15: 180
A16: Publicidad en redes | B16: 120
A17: Total costos fijos mensuales | B17: =SUM(B12:B16) -> 3600

Sheet Caso 1
A1: CASO 1. COSTO UNITARIO REAL DE LA TORTA DE CHOCOLATE DE 1 KG
A2: Complete la columna Importe y los indicadores. Todo con fórmulas.
A4: 1. Materia prima por torta
A5: Insumo | B5: Cantidad | C5: Unidad | D5: Precio unitario (S/) | E5: Importe (S/)
A6: Harina | B6: 0.5 | C6: kg | D6: 4.2 | E6: =B6*D6 -> 2.1
A7: Azúcar | B7: 0.4 | C7: kg | D7: 3.5 | E7: =B7*D7 -> 1.4
A8: Chocolate de cobertura | B8: 0.35 | C8: kg | D8: 28 | E8: =B8*D8 -> 9.8
A9: Huevos | B9: 6 | C9: unidad | D9: 0.55 | E9: =B9*D9 -> 3.3
A10: Mantequilla | B10: 0.25 | C10: kg | D10: 22 | E10: =B10*D10 -> 5.5
A11: Leche | B11: 0.3 | C11: litro | D11: 4 | E11: =B11*D11 -> 1.2
A12: Esencias y polvo de hornear | B12: 1 | C12: global | D12: 1.9 | E12: =B12*D12 -> 1.9
A13: Subtotal materia prima por torta | E13: =SUM(E6:E12) -> 25.2
A15: 2. Otros costos variables por torta
A16: Concepto | B16: Importe (S/)
A17: Empaque: caja, base de cartón y cinta | B17: 2.3
A18: Comisión de venta y delivery | B18: 2.6
A19: Energía variable del horno | B19: 0.9
A20: Subtotal otros costos variables | B20: =SUM(B17:B19) -> 5.8
A22: 3. Indicadores de costo
A23: Costo variable unitario, CVU (S/) | B23: =E13+B20 -> 31
A24: Costos fijos mensuales (S/) | B24: =Datos!B17 -> 3600
A25: Volumen mensual (tortas) | B25: =Datos!B6 -> 400
A26: Costo fijo unitario (S/) | B26: =B24/B25 -> 9
A27: Costo unitario total (S/) | B27: =B23+B26 -> 40
A29: 4. El costo unitario no es un número fijo: depende del volumen
A30: Volumen mensual (tortas) | B30: Costo fijo unitario (S/) | C30: Costo unitario total (S/)
A31: 300 | B31: =$B$24/A31 -> 12 | C31: =$B$23+B31 -> 43
A32: 400 | B32: =$B$24/A32 -> 9 | C32: =$B$23+B32 -> 40
A33: 500 | B33: =$B$24/A33 -> 7.2 | C33: =$B$23+B33 -> 38.2
A35: Conclusión del equipo: | B35: El costo unitario cae al producir más porque el costo fijo se reparte entre más tortas.

Sheet Caso 2
A1: CASO 2. COST-PLUS: EL RECARGO NO ES EL MARGEN
A2: La dueña fija el precio agregando 50% al costo. Compruebe que margen obtiene en realidad.
A4: Costo unitario (S/) | B4: =+'Caso 1'!B27 -> 40
A5: Recargo aplicado por la dueña | B5: 0.5
A6: Precio con Cost-Plus (S/) | B6: =B4*(1+B5) -> 60
A7: Utilidad unitaria (S/) | B7: =B6-B4 -> 20
A8: Recargo comprobado | B8: =B7/B4 -> 0.5
A9: Margen bruto real | B9: =B7/B6 -> 0.33333333
A11: Tabla de conversión: recargo aplicado y margen que realmente produce
A12: Recargo | B12: Precio (S/) | C12: Utilidad unitaria (S/) | D12: Margen bruto resultante | H12: PAYASO | I12: 12:00 - 14:00 | K12: MARTES 22
A13: 0.2 | B13: =$B$4*(1+A13) -> 48 | C13: =B13-$B$4 -> 8 | D13: =C13/B13 -> 0.16666667
A14: 0.3 | B14: =$B$4*(1+A14) -> 52 | C14: =B14-$B$4 -> 12 | D14: =C14/B14 -> 0.23076923 | K14: JUEVES 17 | M14: CINE + BUFFET
A15: 0.4 | B15: =$B$4*(1+A15) -> 56 | C15: =B15-$B$4 -> 16 | D15: =C15/B15 -> 0.28571429
A16: 0.5 | B16: =$B$4*(1+A16) -> 60 | C16: =B16-$B$4 -> 20 | D16: =C16/B16 -> 0.33333333 | H16: CHARADA DE LOBOS | K16: MARTES 15 | M16: MIMICAS | N16: CHARADAS | P16: GASEOSA
A17: 0.6 | B17: =$B$4*(1+A17) -> 64 | C17: =B17-$B$4 -> 24 | D17: =C17/B17 -> 0.375
A18: 0.8 | B18: =$B$4*(1+A18) -> 72 | C18: =B18-$B$4 -> 32 | D18: =C18/B18 -> 0.44444444
A19: 1 | B19: =$B$4*(1+A19) -> 80 | C19: =B19-$B$4 -> 40 | D19: =C19/B19 -> 0.5
A21: Recargo necesario para obtener el margen meta de la empresa | B21: =Datos!B8/(1-Datos!B8) -> 0.66666667
A22: Precio que corresponde a ese recargo (S/) | B22: =B4*(1+B21) -> 66.666667
A24: Conclusión del equipo: | B24: Un recargo de 50% produce solo 33.33% de margen. Para 40% de margen hace falta 66.67% de recargo.

Sheet Caso 3
A1: CASO 3. PRECIO A PARTIR DE UN MARGEN BRUTO DESEADO
A2: Método correcto: Precio = Costo / (1 - margen deseado). Método erróneo frecuente: Costo x (1 + margen).
A4: Costo unitario (S/) | B4: =+'Caso 1'!B27 -> 40
A6: Margen deseado | B6: Precio correcto (S/) | C6: Precio método erróneo (S/) | D6: Margen real del método erróneo | E6: Diferencia por torta (S/) | F6: Diferencia mensual (S/)
A7: 0.3 | B7: =$B$4/(1-A7) -> 57.142857 | C7: =$B$4*(1+A7) -> 52 | D7: =(C7-$B$4)/C7 -> 0.23076923 | E7: =B7-C7 -> 5.1428571 | F7: =E7*Datos!$B$6 -> 2057.1429
A8: 0.35 | B8: =$B$4/(1-A8) -> 61.538462 | C8: =$B$4*(1+A8) -> 54 | D8: =(C8-$B$4)/C8 -> 0.25925926 | E8: =B8-C8 -> 7.5384615 | F8: =E8*Datos!$B$6 -> 3015.3846
A9: 0.4 | B9: =$B$4/(1-A9) -> 66.666667 | C9: =$B$4*(1+A9) -> 56 | D9: =(C9-$B$4)/C9 -> 0.28571429 | E9: =B9-C9 -> 10.666667 | F9: =E9*Datos!$B$6 -> 4266.6667
A10: 0.45 | B10: =$B$4/(1-A10) -> 72.727273 | C10: =$B$4*(1+A10) -> 58 | D10: =(C10-$B$4)/C10 -> 0.31034483 | E10: =B10-C10 -> 14.727273 | F10: =E10*Datos!$B$6 -> 5890.9091
A11: 0.5 | B11: =$B$4/(1-A11) -> 80 | C11: =$B$4*(1+A11) -> 60 | D11: =(C11-$B$4)/C11 -> 0.33333333 | E11: =B11-C11 -> 20 | F11: =E11*Datos!$B$6 -> 8000
A13: Conclusión del equipo: | B13: Con la meta de 40%, usar el método erróneo cuesta S/ 10.67 por torta y S/ 4,266.67 al mes.

Sheet Caso 4
A1: CASO 4. INGENIERÍA DEL MARGEN DEL PORTAFOLIO
A2: Meta de margen bruto de la empresa: ver hoja Datos. Complete de la columna E a la J.
A4: Producto | B4: Costo unitario (S/) | C4: Precio actual (S/) | D4: Unidades por mes | E4: Margen bruto | F4: Cumple meta | G4: Precio meta (S/) | H4: Variación de precio requerida | I4: Ingresos del mes (S/) | J4: Margen del mes (S/)
A5: Torta de chocolate 1 kg | B5: 40 | C5: 60 | D5: 400 | E5: =(C5-B5)/C5 -> 0.33333333 | F5: =IF(E5>=Datos!$B$8,"SI","NO") -> NO | G5: =B5/(1-Datos!$B$8) -> 66.666667 | H5: =G5/C5-1 -> 0.11111111 | I5: =C5*D5 -> 24000 | J5: =(C5-B5)*D5 -> 8000
A6: Cheesecake de maracuyá | B6: 33 | C6: 58 | D6: 120 | E6: =(C6-B6)/C6 -> 0.43103448 | F6: =IF(E6>=Datos!$B$8,"SI","NO") -> SI | G6: =B6/(1-Datos!$B$8) -> 55 | H6: =G6/C6-1 -> -0.051724138 | I6: =C6*D6 -> 6960 | J6: =(C6-B6)*D6 -> 3000
A7: Alfajores caja x 12 | B7: 18 | C7: 25 | D7: 200 | E7: =(C7-B7)/C7 -> 0.28 | F7: =IF(E7>=Datos!$B$8,"SI","NO") -> NO | G7: =B7/(1-Datos!$B$8) -> 30 | H7: =G7/C7-1 -> 0.2 | I7: =C7*D7 -> 5000 | J7: =(C7-B7)*D7 -> 1400
A8: Pan de yema bolsa x 6 | B8: 4.5 | C8: 6 | D8: 2000 | E8: =(C8-B8)/C8 -> 0.25 | F8: =IF(E8>=Datos!$B$8,"SI","NO") -> NO | G8: =B8/(1-Datos!$B$8) -> 7.5 | H8: =G8/C8-1 -> 0.25 | I8: =C8*D8 -> 12000 | J8: =(C8-B8)*D8 -> 3000
A9: Empanada de pollo | B9: 2.8 | C9: 5 | D9: 600 | E9: =(C9-B9)/C9 -> 0.44 | F9: =IF(E9>=Datos!$B$8,"SI","NO") -> SI | G9: =B9/(1-Datos!$B$8) -> 4.6666667 | H9: =G9/C9-1 -> -0.066666667 | I9: =C9*D9 -> 3000 | J9: =(C9-B9)*D9 -> 1320
A10: Totales | I10: =SUM(I5:I9) -> 50960 | J10: =SUM(J5:J9) -> 16720
A12: Margen ponderado real del portafolio | B12: =J10/I10 -> 0.32810047
A13: Promedio simple de los márgenes | B13: =AVERAGE(E5:E9) -> 0.34687356
A14: Producto que más margen aporta en soles | B14: =INDEX(A5:A9,MATCH(MAX(J5:J9),J5:J9,0)) -> Torta de chocolate 1 kg
A15: Producto con la mayor brecha de precio | B15: =INDEX(A5:A9,MATCH(MAX(H5:H9),H5:H9,0)) -> Pan de yema bolsa x 6
A17: Conclusión del equipo: | B17: El margen ponderado es menor que el promedio simple porque el producto de menor margen es el de mayor volumen.

Sheet Caso 5
A1: CASO 5. CLASIFICACIÓN DE COSTOS, MCU Y PUNTO DE EQUILIBRIO
A2: Clasifique cada costo con la lista desplegable y separe la parte fija de la parte variable.
A4: Concepto (mes de 400 tortas) | B4: Importe mensual (S/) | C4: Clasificación | D4: Parte fija (S/) | E4: Parte variable (S/)
A5: Insumos de materia prima | B5: 10080 | C5: Variable | D5: 0 | E5: 10080
A6: Cajas, bases de cartón y cintas | B6: 920 | C6: Variable | D6: 0 | E6: 920
A7: Comisión de venta y delivery | B7: 1040 | C7: Variable | D7: 0 | E7: 1040
A8: Energía del horno: S/ 180 fijos más S/ 0.90 por torta | B8: 540 | C8: Mixto | D8: 180 | E8: 360
A9: Alquiler del local (parte asignada) | B9: 1500 | C9: Fijo | D9: 1500 | E9: 0
A10: Sueldo fijo del maestro pastelero | B10: 1500 | C10: Fijo | D10: 1500 | E10: 0
A11: Depreciación de equipos | B11: 300 | C11: Fijo | D11: 300 | E11: 0
A12: Publicidad en redes | B12: 120 | C12: Fijo | D12: 120 | E12: 0
A13: Totales | D13: =SUM(D5:D12) -> 3600 | E13: =SUM(E5:E12) -> 12400
A15: Volumen mensual (tortas) | B15: =Datos!B6 -> 400
A16: Costo variable unitario, CVU (S/) | B16: =E13/B15 -> 31
A17: Precio de venta actual (S/) | B17: =Datos!B7 -> 60
A18: Margen de contribución unitario, MCU (S/) | B18: =B17-B16 -> 29
A19: Razón de contribución (MCU / Precio) | B19: =B18/B17 -> 0.48333333
A20: Costos fijos mensuales (S/) | B20: =D13 -> 3600
A21: Punto de equilibrio exacto (tortas) | B21: =B20/B18 -> 124.13793
A22: Punto de equilibrio en unidades enteras | B22: =ROUNDUP(B21,0) -> 125
A23: Margen de seguridad sobre el volumen actual | B23: =(B15-B22)/B15 -> 0.6875
A24: Utilidad mensual actual (S/) | B24: =B18*B15-B20 -> 8000
A26: Conclusión del equipo: | B26: Cada torta aporta S/ 29 a los costos fijos; con 125 tortas la línea deja de perder.

Sheet Caso 6
A1: CASO 6. PRECIO, VOLUMEN, INGRESOS Y UTILIDAD
A2: El área comercial estimó cuántas tortas se venderían con cada precio. Complete de la columna D a la I.
A4: Escenario | B4: Precio (S/) | C4: Unidades | D4: Ingresos (S/) | E4: MCU (S/) | F4: Margen de contribución total (S/) | G4: Costos fijos (S/) | H4: Utilidad (S/) | I4: Punto de equilibrio (tortas)
A5: Baja 10% | B5: 54 | C5: 470 | D5: =B5*C5 -> 25380 | E5: =B5-'Caso 5'!$B$16 -> 23 | F5: =E5*C5 -> 10810 | G5: ='Caso 5'!$B$20 -> 3600 | H5: =F5-G5 -> 7210 | I5: =ROUNDUP(G5/E5,0) -> 157
A6: Baja 5% | B6: 57 | C6: 435 | D6: =B6*C6 -> 24795 | E6: =B6-'Caso 5'!$B$16 -> 26 | F6: =E6*C6 -> 11310 | G6: ='Caso 5'!$B$20 -> 3600 | H6: =F6-G6 -> 7710 | I6: =ROUNDUP(G6/E6,0) -> 139
A7: Actual | B7: 60 | C7: 400 | D7: =B7*C7 -> 24000 | E7: =B7-'Caso 5'!$B$16 -> 29 | F7: =E7*C7 -> 11600 | G7: ='Caso 5'!$B$20 -> 3600 | H7: =F7-G7 -> 8000 | I7: =ROUNDUP(G7/E7,0) -> 125
A8: Sube 5% | B8: 63 | C8: 365 | D8: =B8*C8 -> 22995 | E8: =B8-'Caso 5'!$B$16 -> 32 | F8: =E8*C8 -> 11680 | G8: ='Caso 5'!$B$20 -> 3600 | H8: =F8-G8 -> 8080 | I8: =ROUNDUP(G8/E8,0) -> 113
A9: Sube 10% | B9: 66 | C9: 330 | D9: =B9*C9 -> 21780 | E9: =B9-'Caso 5'!$B$16 -> 35 | F9: =E9*C9 -> 11550 | G9: ='Caso 5'!$B$20 -> 3600 | H9: =F9-G9 -> 7950 | I9: =ROUNDUP(G9/E9,0) -> 103
A11: Escenario con mayores ingresos | D11: =INDEX(A5:A9,MATCH(MAX(D5:D9),D5:D9,0)) -> Baja 10%
A12: Escenario con mayor utilidad | D12: =INDEX(A5:A9,MATCH(MAX(H5:H9),H5:H9,0)) -> Sube 5%
A13: Diferencia de utilidad entre el mejor escenario y el actual (S/) | D13: =MAX(H5:H9)-H7 -> 80
A14: Tortas que necesitaría el escenario Baja 10% para igualar la utilidad actual | D14: =(H7+G5)/E5 -> 504.34783
A16: Conclusión del equipo: | B16: El escenario de mayores ingresos no es el de mayor utilidad: bajar el precio vende más y gana menos.

Sheet Caso 7
A1: CASO 7. RULETA DE ESCENARIOS
A2: El docente anuncia un shock. El equipo tiene tres minutos para recalcular y responder con un número.
A4: Shock | B4: Cambio en el CVU (S/) | C4: Cambio en costos fijos (S/) | D4: Precio (S/) | E4: Unidades | F4: CVU nuevo (S/) | G4: MCU (S/) | H4: Utilidad mensual (S/) | I4: Decisión propuesta
A5: 1. El chocolate de cobertura sube 20% | B5: 1.96 | C5: 0 | D5: 60 | E5: 400 | F5: ='Caso 5'!$B$16+B5 -> 32.96 | G5: =D5-F5 -> 27.04 | H5: =G5*E5-('Caso 5'!$B$20+C5) -> 7216
A6: 2. La competencia lanza su torta a S/ 52 y Dulce Sabor baja a S/ 54 | B6: 0 | C6: 0 | D6: 54 | E6: 470 | F6: ='Caso 5'!$B$16+B6 -> 31 | G6: =D6-F6 -> 23 | H6: =G6*E6-('Caso 5'!$B$20+C6) -> 7210
A7: 3. La empresa de delivery sube su comisión en S/ 1.50 por torta | B7: 1.5 | C7: 0 | D7: 60 | E7: 400 | F7: ='Caso 5'!$B$16+B7 -> 32.5 | G7: =D7-F7 -> 27.5 | H7: =G7*E7-('Caso 5'!$B$20+C7) -> 7400
A8: 4. El alquiler asignado sube S/ 450 al mes | B8: 0 | C8: 450 | D8: 60 | E8: 400 | F8: ='Caso 5'!$B$16+B8 -> 31 | G8: =D8-F8 -> 29 | H8: =G8*E8-('Caso 5'!$B$20+C8) -> 7550
A9: 5. Campaña: 10% de descuento y el volumen sube a 500 tortas | B9: 0 | C9: 0 | D9: 54 | E9: 500 | F9: ='Caso 5'!$B$16+B9 -> 31 | G9: =D9-F9 -> 23 | H9: =G9*E9-('Caso 5'!$B$20+C9) -> 7900
A11: Utilidad mensual sin shock (referencia, S/) | B11: ='Caso 5'!B24 -> 8000
A12: Shock que más daña la utilidad | B12: =INDEX(A5:A9,MATCH(MIN(H5:H9),H5:H9,0)) -> 2. La competencia lanza su torta a S/ 52 y Dulce Sabor baja a S/ 54

Sheet Reto
A1: ESTACIÓN ANALISTA SENIOR
A2: Trabajo individual complementario. Use la función de demanda estimada por el área comercial.
A4: Función de demanda: Unidades = a - b x Precio
A5: a | B5: 1100
A6: b | B6: 11.666667
A7: Comprobación: unidades al precio actual | B7: =$B$5-$B$6*Datos!B7 -> 400
A9: Reto 1. Matriz de sensibilidad: utilidad mensual según precio y costo variable unitario
A10: Filas: precio. Columnas: CVU. Use referencias mixtas y una sola fórmula copiada.
A11: Precio / CVU | B11: 29 | C11: 30 | D11: 31 | E11: 32 | F11: 33 | G11: 34 | H11: 35
A12: 54 | B12: =($A12-B$11)*($B$5-$B$6*$A12)-'Caso 5'!$B$20 -> 8150 | C12: =($A12-C$11)*($B$5-$B$6*$A12)-'Caso 5'!$B$20 -> 7680 | D12: =($A12-D$11)*($B$5-$B$6*$A12)-'Caso 5'!$B$20 -> 7210 | E12: =($A12-E$11)*($B$5-$B$6*$A12)-'Caso 5'!$B$20 -> 6740 | F12: =($A12-F$11)*($B$5-$B$6*$A12)-'Caso 5'!$B$20 -> 6270 | G12: =($A12-G$11)*($B$5-$B$6*$A12)-'Caso 5'!$B$20 -> 5800 | H12: =($A12-H$11)*($B$5-$B$6*$A12)-'Caso 5'!$B$20 -> 5330
A13: 56 | B13: =($A13-B$11)*($B$5-$B$6*$A13)-'Caso 5'!$B$20 -> 8460 | C13: =($A13-C$11)*($B$5-$B$6*$A13)-'Caso 5'!$B$20 -> 8013.3333 | D13: =($A13-D$11)*($B$5-$B$6*$A13)-'Caso 5'!$B$20 -> 7566.6667 | E13: =($A13-E$11)*($B$5-$B$6*$A13)-'Caso 5'!$B$20 -> 7120 | F13: =($A13-F$11)*($B$5-$B$6*$A13)-'Caso 5'!$B$20 -> 6673.3333 | G13: =($A13-G$11)*($B$5-$B$6*$A13)-'Caso 5'!$B$20 -> 6226.6667 | H13: =($A13-H$11)*($B$5-$B$6*$A13)-'Caso 5'!$B$20 -> 5780
A14: 58 | B14: =($A14-B$11)*($B$5-$B$6*$A14)-'Caso 5'!$B$20 -> 8676.6667 | C14: =($A14-C$11)*($B$5-$B$6*$A14)-'Caso 5'!$B$20 -> 8253.3333 | D14: =($A14-D$11)*($B$5-$B$6*$A14)-'Caso 5'!$B$20 -> 7830 | E14: =($A14-E$11)*($B$5-$B$6*$A14)-'Caso 5'!$B$20 -> 7406.6667 | F14: =($A14-F$11)*($B$5-$B$6*$A14)-'Caso 5'!$B$20 -> 6983.3333 | G14: =($A14-G$11)*($B$5-$B$6*$A14)-'Caso 5'!$B$20 -> 6560 | H14: =($A14-H$11)*($B$5-$B$6*$A14)-'Caso 5'!$B$20 -> 6136.6667
A15: 60 | B15: =($A15-B$11)*($B$5-$B$6*$A15)-'Caso 5'!$B$20 -> 8800 | C15: =($A15-C$11)*($B$5-$B$6*$A15)-'Caso 5'!$B$20 -> 8400 | D15: =($A15-D$11)*($B$5-$B$6*$A15)-'Caso 5'!$B$20 -> 8000 | E15: =($A15-E$11)*($B$5-$B$6*$A15)-'Caso 5'!$B$20 -> 7600 | F15: =($A15-F$11)*($B$5-$B$6*$A15)-'Caso 5'!$B$20 -> 7200 | G15: =($A15-G$11)*($B$5-$B$6*$A15)-'Caso 5'!$B$20 -> 6800 | H15: =($A15-H$11)*($B$5-$B$6*$A15)-'Caso 5'!$B$20 -> 6400
A16: 62 | B16: =($A16-B$11)*($B$5-$B$6*$A16)-'Caso 5'!$B$20 -> 8830 | C16: =($A16-C$11)*($B$5-$B$6*$A16)-'Caso 5'!$B$20 -> 8453.3333 | D16: =($A16-D$11)*($B$5-$B$6*$A16)-'Caso 5'!$B$20 -> 8076.6667 | E16: =($A16-E$11)*($B$5-$B$6*$A16)-'Caso 5'!$B$20 -> 7700 | F16: =($A16-F$11)*($B$5-$B$6*$A16)-'Caso 5'!$B$20 -> 7323.3333 | G16: =($A16-G$11)*($B$5-$B$6*$A16)-'Caso 5'!$B$20 -> 6946.6667 | H16: =($A16-H$11)*($B$5-$B$6*$A16)-'Caso 5'!$B$20 -> 6570
A17: 64 | B17: =($A17-B$11)*($B$5-$B$6*$A17)-'Caso 5'!$B$20 -> 8766.6667 | C17: =($A17-C$11)*($B$5-$B$6*$A17)-'Caso 5'!$B$20 -> 8413.3333 | D17: =($A17-D$11)*($B$5-$B$6*$A17)-'Caso 5'!$B$20 -> 8060 | E17: =($A17-E$11)*($B$5-$B$6*$A17)-'Caso 5'!$B$20 -> 7706.6667 | F17: =($A17-F$11)*($B$5-$B$6*$A17)-'Caso 5'!$B$20 -> 7353.3333 | G17: =($A17-G$11)*($B$5-$B$6*$A17)-'Caso 5'!$B$20 -> 7000 | H17: =($A17-H$11)*($B$5-$B$6*$A17)-'Caso 5'!$B$20 -> 6646.6667
A18: 66 | B18: =($A18-B$11)*($B$5-$B$6*$A18)-'Caso 5'!$B$20 -> 8610 | C18: =($A18-C$11)*($B$5-$B$6*$A18)-'Caso 5'!$B$20 -> 8280 | D18: =($A18-D$11)*($B$5-$B$6*$A18)-'Caso 5'!$B$20 -> 7950 | E18: =($A18-E$11)*($B$5-$B$6*$A18)-'Caso 5'!$B$20 -> 7620 | F18: =($A18-F$11)*($B$5-$B$6*$A18)-'Caso 5'!$B$20 -> 7290 | G18: =($A18-G$11)*($B$5-$B$6*$A18)-'Caso 5'!$B$20 -> 6960 | H18: =($A18-H$11)*($B$5-$B$6*$A18)-'Caso 5'!$B$20 -> 6630
A20: Reto 2. Elasticidad precio-demanda en el precio actual
A21: Elasticidad = -b x Precio / Unidades | B21: =-$B$6*Datos!B7/$B$7 -> -1.75
A22: Interpretación (elástica o inelástica) | B22: Elastica: 1% de subida de precio reduce 1.75% las unidades.
A24: Reto 3. Precio que maximiza la utilidad
A25: Precio (S/) | B25: Unidades | C25: MCU (S/) | D25: Utilidad (S/)
A26: 58 | B26: =$B$5-$B$6*A26 -> 423.33333 | C26: =A26-'Caso 5'!$B$16 -> 27 | D26: =C26*B26-'Caso 5'!$B$20 -> 7830
A27: 58.25 | B27: =$B$5-$B$6*A27 -> 420.41667 | C27: =A27-'Caso 5'!$B$16 -> 27.25 | D27: =C27*B27-'Caso 5'!$B$20 -> 7856.3542
A28: 58.5 | B28: =$B$5-$B$6*A28 -> 417.5 | C28: =A28-'Caso 5'!$B$16 -> 27.5 | D28: =C28*B28-'Caso 5'!$B$20 -> 7881.25
A29: 58.75 | B29: =$B$5-$B$6*A29 -> 414.58333 | C29: =A29-'Caso 5'!$B$16 -> 27.75 | D29: =C29*B29-'Caso 5'!$B$20 -> 7904.6875
A30: 59 | B30: =$B$5-$B$6*A30 -> 411.66667 | C30: =A30-'Caso 5'!$B$16 -> 28 | D30: =C30*B30-'Caso 5'!$B$20 -> 7926.6667
A31: 59.25 | B31: =$B$5-$B$6*A31 -> 408.75 | C31: =A31-'Caso 5'!$B$16 -> 28.25 | D31: =C31*B31-'Caso 5'!$B$20 -> 7947.1875
A32: 59.5 | B32: =$B$5-$B$6*A32 -> 405.83333 | C32: =A32-'Caso 5'!$B$16 -> 28.5 | D32: =C32*B32-'Caso 5'!$B$20 -> 7966.25
A33: 59.75 | B33: =$B$5-$B$6*A33 -> 402.91667 | C33: =A33-'Caso 5'!$B$16 -> 28.75 | D33: =C33*B33-'Caso 5'!$B$20 -> 7983.8542
A34: 60 | B34: =$B$5-$B$6*A34 -> 400 | C34: =A34-'Caso 5'!$B$16 -> 29 | D34: =C34*B34-'Caso 5'!$B$20 -> 8000
A35: 60.25 | B35: =$B$5-$B$6*A35 -> 397.08333 | C35: =A35-'Caso 5'!$B$16 -> 29.25 | D35: =C35*B35-'Caso 5'!$B$20 -> 8014.6875
A36: 60.5 | B36: =$B$5-$B$6*A36 -> 394.16667 | C36: =A36-'Caso 5'!$B$16 -> 29.5 | D36: =C36*B36-'Caso 5'!$B$20 -> 8027.9167
A37: 60.75 | B37: =$B$5-$B$6*A37 -> 391.25 | C37: =A37-'Caso 5'!$B$16 -> 29.75 | D37: =C37*B37-'Caso 5'!$B$20 -> 8039.6875
... A66: 68 | B66: =$B$5-$B$6*A66 -> 306.66667 | C66: =A66-'Caso 5'!$B$16 -> 37 | D66: =C66*B66-'Caso 5'!$B$20 -> 7746.6667
A68: Utilidad máxima (S/) | B68: =MAX(D26:D66) -> 8081.3542
A69: Precio que la produce (S/) | B69: =INDEX(A26:A66,MATCH(MAX(D26:D66),D26:D66,0)) -> 62.75
A70: Diferencia frente a la utilidad actual (S/) | B70: =B68-'Caso 5'!B24 -> 81.354167
A72: Reto 4. CVU necesario para una utilidad meta de S/ 9,000 al precio actual | B72: =Datos!B7-(9000+'Caso 5'!B20)/Datos!B6 -> 28.5
A73: Reducción exigida al costo variable unitario | B73: =B72/'Caso 5'!B16-1 -> -0.080645161
